{
 "absolute_value": 0,
 "align_labels_right": 0,
 "creation": "2023-02-15 17:10:19.859905",
 "custom_format": 1,
 "default_print_language": "en-US",
 "disabled": 0,
 "doc_type": "Tally Sales Invoice",
 "docstatus": 0,
 "doctype": "Print Format",
 "font": "Default",
 "html": "<pre>\n{{   doc.output|safe }}\n</pre>\n",
 "idx": 0,
 "line_breaks": 0,
 "modified": "2023-02-15 20:44:09.564418",
 "modified_by": "Administrator",
 "module": "Tally Api",
 "name": "tally invoice",
 "owner": "Administrator",
 "print_format_builder": 0,
 "print_format_type": "Jinja",
 "raw_printing": 0,
 "show_section_headings": 0,
 "standard": "Yes"
}